aiohglib/__init__.py
aiohglib/client.py
aiohglib/context.py
aiohglib/error.py
aiohglib/merge.py
aiohglib/templates.py
aiohglib/util.py
aiohglib-1.5.dist-info/LICENSE
aiohglib-1.5.dist-info/METADATA
aiohglib-1.5.dist-info/WHEEL
aiohglib-1.5.dist-info/top_level.txt
aiohglib-1.5.dist-info/RECORD
