Metadata-Version: 2.1
Name: aiohglib
Version: 1.5
Summary: Mercurial Python asynchronous library
Home-page: https://bitbucket.org/515k4/aiohglib/
Author: Michal Šiška
Author-email: michal.515k4@gmail.com
License: MIT
Platform: UNKNOWN
Classifier: Development Status :: 4 - Beta
Classifier: Intended Audience :: Developers
Classifier: License :: OSI Approved :: MIT License
Classifier: Operating System :: OS Independent
Classifier: Programming Language :: Python :: 3 :: Only
Classifier: Programming Language :: Python :: 3
Classifier: Programming Language :: Python :: 3.6
Classifier: Programming Language :: Python :: 3.7
Classifier: Programming Language :: Python :: 3.8
Classifier: Programming Language :: Python :: 3.9
Classifier: Programming Language :: Python
Classifier: Topic :: Software Development :: Version Control
Requires-Python: >=3.6
License-File: LICENSE
Requires-Dist: pytz
